spyder/__init__.py
spyder/dependencies.py
spyder/otherplugins.py
spyder/pil_patch.py
spyder/py3compat.py
spyder/pyplot.py
spyder/requirements.py
spyder/api/__init__.py
spyder/api/completion.py
spyder/api/editor.py
spyder/api/editorextension.py
spyder/api/manager.py
spyder/api/panel.py
spyder/api/plugins.py
spyder/api/preferences.py
spyder/api/translations.py
spyder/app/__init__.py
spyder/app/cli_options.py
spyder/app/mac_stylesheet.qss
spyder/app/mainwindow.py
spyder/app/restart.py
spyder/app/start.py
spyder/app/tour.py
spyder/app/utils.py
spyder/config/__init__.py
spyder/config/appearance.py
spyder/config/base.py
spyder/config/fonts.py
spyder/config/gui.py
spyder/config/lsp.py
spyder/config/main.py
spyder/config/manager.py
spyder/config/user.py
spyder/config/utils.py
spyder/fonts/IdeFont.sfd
spyder/fonts/spyder-charmap.json
spyder/fonts/spyder.ttf
spyder/images/CloseButton.png
spyder/images/LICENSE.txt
spyder/images/advanced.png
spyder/images/arredit.png
spyder/images/arrow.png
spyder/images/binary_dark.svg
spyder/images/binary_light.svg
spyder/images/bold.png
spyder/images/browser.png
spyder/images/chevron-left.png
spyder/images/chevron-right.png
spyder/images/code_fork.png
spyder/images/dictedit.png
spyder/images/eyedropper.png
spyder/images/file_type_tex_dark.svg
spyder/images/file_type_tex_light.svg
spyder/images/genprefs.png
spyder/images/help.png
spyder/images/italic.png
spyder/images/keyboard.png
spyder/images/kite.gif
spyder/images/kite_copilot.png
spyder/images/kite_dark.svg
spyder/images/kite_light.svg
spyder/images/matplotlib.png
spyder/images/none.png
spyder/images/not_found.png
spyder/images/notebook_dark.svg
spyder/images/notebook_light.svg
spyder/images/options.svg
spyder/images/pythonpath.png
spyder/images/splash.svg
spyder/images/spyder.png
spyder/images/spyder.svg
spyder/images/spyder_dark.png
spyder/images/spyder_dark.svg
spyder/images/spyder_kite.svg
spyder/images/spyder_kite_dark.svg
spyder/images/tour-spyder-logo.png
spyder-4.1.2.dist-info/AUTHORS.txt
spyder-4.1.2.dist-info/LICENSE.txt
spyder-4.1.2.dist-info/METADATA
spyder-4.1.2.dist-info/NOTICE.txt
spyder-4.1.2.dist-info/WHEEL
spyder-4.1.2.dist-info/entry_points.txt
spyder-4.1.2.dist-info/top_level.txt
spyder-4.1.2.dist-info/RECORD
