Metadata-Version: 1.1
Name: spyder
Version: 4.1.2
Summary: The Scientific Python Development Environment
Home-page: https://www.spyder-ide.org/
Author: The Spyder Project Contributors
Author-email: spyderlib@googlegroups.com
License: MIT
Download-URL: https://www.spyder-ide.org/#fh5co-download
Keywords: PyQt5 editor console widgets IDE science data analysis IPython
Platform: Windows
Platform: Linux
Platform: Mac OS-X
Classifier: License :: OSI Approved :: MIT License
Classifier: Operating System :: MacOS
Classifier: Operating System :: Microsoft :: Windows
Classifier: Operating System :: POSIX :: Linux
Classifier: Programming Language :: Python :: 2
Classifier: Programming Language :: Python :: 2.7
Classifier: Programming Language :: Python :: 3
Classifier: Programming Language :: Python :: 3.4
Classifier: Programming Language :: Python :: 3.5
Classifier: Programming Language :: Python :: 3.6
Classifier: Programming Language :: Python :: 3.7
Classifier: Development Status :: 5 - Production/Stable
Classifier: Intended Audience :: Education
Classifier: Intended Audience :: Science/Research
Classifier: Intended Audience :: Developers
Classifier: Topic :: Scientific/Engineering
Classifier: Topic :: Software Development :: Widget Sets
